[
    {
        "id": 1,
        "contactPerson": 4,
        "items": [1,2,3],
        "dataOrder": "23/02/2022",
        "adress": "Rua silveira 45 4400-027",
        "paymentMethod": "Visa",
        "amount": 200.05,
        "paid":true,
        "shipped": false,
        "status": 1
    },{
        "id": 2,
        "contactPerson": 1,
        "items": [1,2,3],
        "dataOrder": "23/02/2022",
        "adress": "Rua silveira 45 4400-027",
        "paymentMethod": "Visa",
        "amount": 200.05,
        "paid":true,
        "shipped": false,
        "status": 1
    },{
        "id": 3,
        "contactPerson": 2,
        "items": [1,2,3],
        "dataOrder": "23/02/2022",
        "adress": "Rua silveira 45 4400-027",
        "paymentMethod": "Visa",
        "amount": 200.05,
        "paid":true,
        "shipped": false,
        "status": 1
    },{
        "id": 14,
        "contactPerson": 3,
        "items": [1,2,3],
        "dataOrder": "23/02/2022",
        "adress": "Rua silveira 45 4400-027",
        "paymentMethod": "Visa",
        "amount": 200.05,
        "paid":true,
        "shipped": false,
        "status": 1
    },{
        "id": 5,
        "contactPerson": 5,
        "items": [1,2,3],
        "dataOrder": "23/02/2022",
        "adress": "Rua silveira 45 4400-027",
        "paymentMethod": "Visa",
        "amount": 200.05,
        "paid":true,
        "shipped": false,
        "status": 1
    },{
        "id": 6,
        "contactPerson": 6,
        "items": [1,2,3],
        "dataOrder": "23/02/2022",
        "adress": "Rua silveira 45 4400-027",
        "paymentMethod": "Visa",
        "amount": 200.05,
        "paid":true,
        "shipped": false,
        "status": 1
    },{
        "id": 7,
        "contactPerson": 8,
        "items": [1,2,3],
        "dataOrder": "23/02/2022",
        "adress": "Rua silveira 45 4400-027",
        "paymentMethod": "Visa",
        "amount": 200.05,
        "paid":true,
        "shipped": false,
        "status": 1
    },{
        "id": 8,
        "contactPerson": 6,
        "items": [1,2,3],
        "dataOrder": "23/02/2022",
        "adress": "Rua silveira 45 4400-027",
        "paymentMethod": "Visa",
        "amount": 200.05,
        "paid":true,
        "shipped": false,
        "status": 1
    },{
        "id": 9,
        "contactPerson": 10,
        "items": [1,2,3],
        "dataOrder": "23/02/2022",
        "adress": "Rua silveira 45 4400-027",
        "paymentMethod": "Visa",
        "amount": 200.05,
        "paid":true,
        "shipped": false,
        "status": 1
    },{
        "id": 10,
        "contactPerson": 9,
        "items": [1,2,3],
        "dataOrder": "23/02/2022",
        "adress": "Rua silveira 45 4400-027",
        "paymentMethod": "Visa",
        "amount": 200.05,
        "paid":true,
        "shipped": false,
        "status": 1
    },{
        "id": 11,
        "contactPerson": 4,
        "items": [1,2,3],
        "dataOrder": "23/02/2022",
        "adress": "Rua silveira 45 4400-027",
        "paymentMethod": "Visa",
        "amount": 200.05,
        "paid":true,
        "shipped": false,
        "status": 1
    },{
        "id": 12,
        "contactPerson": 4,
        "items": [1,2,3],
        "dataOrder": "23/02/2022",
        "adress": "Rua silveira 45 4400-027",
        "paymentMethod": "Visa",
        "amount": 200.05,
        "paid":true,
        "shipped": false,
        "status": 1
    },{
        "id": 13,
        "contactPerson": 4,
        "items": [1,2,3],
        "dataOrder": "23/02/2022",
        "adress": "Rua silveira 45 4400-027",
        "paymentMethod": "Visa",
        "amount": 200.05,
        "paid":true,
        "shipped": false,
        "status": 1
    }
]